MySQLBridgeData/__init__.py
MySQLBridgeData/my_module.py
MySQLBridgeData-0.1.0.3.dist-info/LICENSE
MySQLBridgeData-0.1.0.3.dist-info/METADATA
MySQLBridgeData-0.1.0.3.dist-info/WHEEL
MySQLBridgeData-0.1.0.3.dist-info/top_level.txt
MySQLBridgeData-0.1.0.3.dist-info/RECORD
