Metadata-Version: 2.1
Name: MySQLBridgeData
Version: 0.1.0.3
Summary: A lightweight Python module to simplify MySQL database connections and queries.
Home-page: https://github.com/Manti-Rashee/MySQLDataBridge
Author: H-Rasheed
Author-email: rsm878yourkhan@gmail.com
Classifier: Programming Language :: Python :: 3
Classifier: License :: OSI Approved :: MIT License
Classifier: Operating System :: OS Independent
Requires-Python: >=3.6
License-File: LICENSE
Requires-Dist: mysql-connector-python
